md2epub/__init__.py
md2epub/cli.py
md2epub/converter.py
md2epub/css_template.py
md2epub/epub_builder.py
md2epub/story_creation/__init__.py
md2epub/story_creation/agents.py
md2epub/story_creation/prompts.py
md2epub/story_creation/tools.py
md2epub/story_creation/workflow.py
md2epub-0.3.0.dist-info/licenses/LICENSE
md2epub-0.3.0.dist-info/METADATA
md2epub-0.3.0.dist-info/WHEEL
md2epub-0.3.0.dist-info/entry_points.txt
md2epub-0.3.0.dist-info/top_level.txt
md2epub-0.3.0.dist-info/RECORD
