Metadata-Version: 2.4
Name: md2epub
Version: 0.3.0
Summary: A library and CLI to convert Markdown to Epub
Classifier: Programming Language :: Python :: 3
Classifier: License :: OSI Approved :: MIT License
Classifier: Operating System :: OS Independent
Requires-Python: >=3.12
License-File: LICENSE
Requires-Dist: ebooklib
Requires-Dist: markdown
Requires-Dist: click
Requires-Dist: PyYAML
Requires-Dist: cookiecutter
Requires-Dist: langgraph
Requires-Dist: langchain
Requires-Dist: langchain_openai
Requires-Dist: python-dotenv
Provides-Extra: dev
Requires-Dist: pytest; extra == "dev"
Requires-Dist: pytest-cov; extra == "dev"
Requires-Dist: pre-commit; extra == "dev"
Requires-Dist: nbstripout; extra == "dev"
Requires-Dist: mkdocs; extra == "dev"
Requires-Dist: mkdocstrings[python]; extra == "dev"
Requires-Dist: jupyter; extra == "dev"
Requires-Dist: ipykernel; extra == "dev"
Dynamic: license-file
